[{"from":0,"to":1},{"from":2,"to":1},{"from":3,"to":1},{"from":4,"to":1},{"from":5,"to":1},{"from":6,"to":1},{"from":7,"to":1},{"from":8,"to":1},{"from":9,"to":1},{"from":10,"to":1},{"from":11,"to":1},{"from":12,"to":1},{"from":13,"to":1},{"from":14,"to":1},{"from":15,"to":1},{"from":16,"to":1},{"from":17,"to":1},{"from":18,"to":1},{"from":19,"to":1},{"from":20,"to":1},{"from":21,"to":1},{"from":22,"to":1},{"from":23,"to":1},{"from":24,"to":1},{"from":1,"to":25},{"from":26,"to":25},{"from":27,"to":25},{"from":28,"to":25},{"from":29,"to":25},{"from":30,"to":25},{"from":31,"to":25},{"from":32,"to":25},{"from":33,"to":25},{"from":34,"to":25},{"from":35,"to":25},{"from":1,"to":36},{"from":37,"to":36},{"from":38,"to":36},{"from":39,"to":36},{"from":1,"to":40},{"from":41,"to":40},{"from":1,"to":42},{"from":43,"to":42},{"from":1,"to":44},{"from":45,"to":44},{"from":0,"to":46},{"from":46,"to":47},{"from":46,"to":48},{"from":46,"to":49}]